hidden_regime/__init__.py
hidden_regime/_version.py
hidden_regime/analysis.py
hidden_regime/analysis/README.md
hidden_regime/analysis/__init__.py
hidden_regime/analysis/case_study.py
hidden_regime/analysis/financial.py
hidden_regime/analysis/indicator_comparison.py
hidden_regime/analysis/market_event_study.py
hidden_regime/analysis/performance.py
hidden_regime/analysis/regime_evolution.py
hidden_regime/analysis/signal_attribution.py
hidden_regime/analysis/technical_indicators.py
hidden_regime/config/README.md
hidden_regime/config/__init__.py
hidden_regime/config/analysis.py
hidden_regime/config/base.py
hidden_regime/config/case_study.py
hidden_regime/config/data.py
hidden_regime/config/model.py
hidden_regime/config/observation.py
hidden_regime/config/report.py
hidden_regime/config/simulation.py
hidden_regime/data/README.md
hidden_regime/data/__init__.py
hidden_regime/data/collectors.py
hidden_regime/data/exporters.py
hidden_regime/data/financial.py
hidden_regime/factories/README.md
hidden_regime/factories/__init__.py
hidden_regime/factories/components.py
hidden_regime/factories/pipeline.py
hidden_regime/financial/README.md
hidden_regime/financial/__init__.py
hidden_regime/financial/analysis.py
hidden_regime/financial/config.py
hidden_regime/financial/regime_characterizer.py
hidden_regime/financial/signal_generation.py
hidden_regime/models/README.md
hidden_regime/models/README.md.backup
hidden_regime/models/__init__.py
hidden_regime/models/algorithms.py
hidden_regime/models/config.py
hidden_regime/models/hmm.py
hidden_regime/models/utils.py
hidden_regime/observations/README.md
hidden_regime/observations/__init__.py
hidden_regime/observations/base.py
hidden_regime/observations/financial.py
hidden_regime/pipeline/README.md
hidden_regime/pipeline/__init__.py
hidden_regime/pipeline/core.py
hidden_regime/pipeline/interfaces.py
hidden_regime/pipeline/temporal.py
hidden_regime/reports/README.md
hidden_regime/reports/__init__.py
hidden_regime/reports/case_study.py
hidden_regime-1.1.1.dist-info/licenses/LICENSE
hidden_regime-1.1.1.dist-info/METADATA
hidden_regime-1.1.1.dist-info/WHEEL
hidden_regime-1.1.1.dist-info/entry_points.txt
hidden_regime-1.1.1.dist-info/top_level.txt
hidden_regime-1.1.1.dist-info/RECORD
