Metadata-Version: 2.4
Name: hidden-regime
Version: 1.1.1
Summary: Market regime detection using Hidden Markov Models with Bayesian uncertainty quantification
Author-email: aoaustin <contact@hiddenregime.com>
License: MIT
Project-URL: Homepage, https://hiddenregime.com
Project-URL: Documentation, https://docs.hiddenregime.com
Project-URL: Repository, https://github.com/hidden-regime/hidden-regime
Project-URL: Issues, https://github.com/hidden-regime/hidden-regime/issues
Project-URL: Changelog, https://github.com/hidden-regime/hidden-regime/blob/main/CHANGELOG.md
Project-URL: Source Code, https://github.com/hidden-regime/hidden-regime
Project-URL: Bug Reports, https://github.com/hidden-regime/hidden-regime/issues
Project-URL: Feature Requests, https://github.com/hidden-regime/hidden-regime/issues
Keywords: finance,trading,regimes,hmm,hidden-markov-models,bayesian,machine-learning,market-data,quantitative-finance,algorithmic-trading,financial-analysis,time-series,regime-detection,volatility,risk-management
Classifier: Development Status :: 5 - Production/Stable
Classifier: Intended Audience :: Financial and Insurance Industry
Classifier: Intended Audience :: Developers
Classifier: Intended Audience :: Science/Research
Classifier: Topic :: Office/Business :: Financial :: Investment
Classifier: Topic :: Scientific/Engineering :: Artificial Intelligence
Classifier: Topic :: Scientific/Engineering :: Information Analysis
Classifier: Operating System :: OS Independent
Classifier: Programming Language :: Python :: 3
Classifier: Programming Language :: Python :: 3.10
Classifier: Programming Language :: Python :: 3.11
Classifier: Programming Language :: Python :: 3.12
Classifier: Programming Language :: Python :: 3 :: Only
Classifier: Natural Language :: English
Classifier: Environment :: Console
Classifier: Typing :: Typed
Requires-Python: >=3.10
License-File: LICENSE
Requires-Dist: numpy>=2.3.2
Requires-Dist: pandas>=2.3.2
Requires-Dist: scipy>=1.7.0
Requires-Dist: matplotlib>=3.4.0
Requires-Dist: seaborn>=0.11.0
Requires-Dist: tqdm>=4.50.0
Requires-Dist: yfinance>=0.2.0
Requires-Dist: ta>=0.10.2
Requires-Dist: scikit-learn>=1.0.0
Provides-Extra: visualization
Requires-Dist: plotly>=5.0.0; extra == "visualization"
Requires-Dist: Pillow>=9.0.0; extra == "visualization"
Provides-Extra: mcp
Requires-Dist: fastmcp>=2.0.0; extra == "mcp"
Requires-Dist: pydantic>=2.0.0; extra == "mcp"
Provides-Extra: dev
Requires-Dist: pytest>=8.4.2; extra == "dev"
Requires-Dist: pytest-cov>=7.0.0; extra == "dev"
Requires-Dist: pytest-xdist>=3.0.0; extra == "dev"
Requires-Dist: pytest-benchmark>=5.1.0; extra == "dev"
Requires-Dist: pytest-asyncio>=0.23.0; extra == "dev"
Requires-Dist: pytest-timeout>=2.2.0; extra == "dev"
Requires-Dist: psutil>=7.0.0; extra == "dev"
Requires-Dist: black>=25.1.0; extra == "dev"
Requires-Dist: isort>=6.0.1; extra == "dev"
Requires-Dist: flake8>=7.3.0; extra == "dev"
Requires-Dist: mypy>=1.0.0; extra == "dev"
Requires-Dist: bandit[toml]>=1.7.0; extra == "dev"
Requires-Dist: tox>=4.0.0; extra == "dev"
Requires-Dist: build>=1.3.0; extra == "dev"
Requires-Dist: twine>=6.2.0; extra == "dev"
Provides-Extra: docs
Requires-Dist: sphinx>=8.2.3; extra == "docs"
Requires-Dist: sphinx-rtd-theme>=3.0.2; extra == "docs"
Requires-Dist: myst-parser>=4.0.1; extra == "docs"
Requires-Dist: sphinx-autodoc-typehints>=3.2.0; extra == "docs"
Provides-Extra: all
Requires-Dist: hidden-regime[dev,docs,mcp,visualization]; extra == "all"
Dynamic: license-file
